wrapt_timeout_decorator/__init__.py
wrapt_timeout_decorator/__init__conf__.py
wrapt_timeout_decorator/py.typed
wrapt_timeout_decorator/wrap_function_multiprocess.py
wrapt_timeout_decorator/wrap_helper.py
wrapt_timeout_decorator/wrapt_timeout_decorator.py
wrapt_timeout_decorator/wrapt_timeout_decorator_cli.py
wrapt_timeout_decorator-1.5.0.dist-info/LICENSE
wrapt_timeout_decorator-1.5.0.dist-info/METADATA
wrapt_timeout_decorator-1.5.0.dist-info/WHEEL
wrapt_timeout_decorator-1.5.0.dist-info/entry_points.txt
wrapt_timeout_decorator-1.5.0.dist-info/top_level.txt
wrapt_timeout_decorator-1.5.0.dist-info/RECORD
