Metadata-Version: 2.1
Name: wrapt_timeout_decorator
Version: 1.5.0
Summary: The better timout decorator
Author-email: Robert Nowotny <bitranox@gmail.com>
License: MIT
Project-URL: Homepage, https://github.com/bitranox/wrapt_timeout_decorator
Project-URL: Documentation, https://github.com/bitranox/wrapt_timeout_decorator/blob/master/README.rst
Project-URL: Repository, https://github.com/bitranox/wrapt_timeout_decorator.git
Project-URL: Changelog, https://github.com/bitranox/wrapt_timeout_decorator/blob/master/CHANGES.rst
Classifier: Development Status :: 5 - Production/Stable
Classifier: Intended Audience :: Developers
Classifier: License :: OSI Approved :: MIT License
Classifier: Natural Language :: English
Classifier: Operating System :: OS Independent
Classifier: Programming Language :: Python
Classifier: Topic :: Software Development :: Libraries :: Python Modules
Requires-Python: >=3.8.0
License-File: LICENSE
Requires-Dist: cli-exit-tools
Requires-Dist: lib-detect-testenv
Requires-Dist: multiprocess
Requires-Dist: psutil
Requires-Dist: wrapt
Requires-Dist: dill ; sys_platform != "win32"
Requires-Dist: dill !=0.3.5,!=0.3.5.1,>0.3.0 ; sys_platform == "win32"
Provides-Extra: test
Requires-Dist: black ; extra == 'test'
Requires-Dist: codecov ; extra == 'test'
Requires-Dist: coloredlogs ; extra == 'test'
Requires-Dist: coverage ; extra == 'test'
Requires-Dist: flake8 ; extra == 'test'
Requires-Dist: mypy ; extra == 'test'
Requires-Dist: pytest ; extra == 'test'
Requires-Dist: pytest-cov ; extra == 'test'
Requires-Dist: pytest-runner ; extra == 'test'
Requires-Dist: readme-renderer ; extra == 'test'
